{
    "taskDefinitionArn": "arn:aws:ecs:us-east-2:926780917917:task-definition/testapi:1",
    "containerDefinitions": [
        {
            "name": "testapi",
            "image": "926780917917.dkr.ecr.us-east-2.amazonaws.com/venhost",
            "cpu": 0,
            "portMappings": [
                {
                    "name": "testapi-5001-tcp",
                    "containerPort": 5001,
                    "hostPort": 5001,
                    "protocol": "tcp",
                    "appProtocol": "http"
                }
            ],
            "essential": true,
            "environment": [
                {
                    "name": "SITE",
                    "value": "testapi.com"
                }
            ],
            "environmentFiles": [],
            "mountPoints": [],
            "volumesFrom": [],
            "ulimits": [],
            "logConfiguration": {
                "logDriver": "awslogs",
                "options": {
                    "awslogs-create-group": "true",
                    "awslogs-group": "/ecs/testapi",
                    "awslogs-region": "us-east-2",
                    "awslogs-stream-prefix": "ecs"
                }
            }
        }
    ],
    "family": "testapi",
    "executionRoleArn": "arn:aws:iam::926780917917:role/ecsTaskExecutionRole",
    "networkMode": "awsvpc",
    "revision": 1,
    "volumes": [],
    "status": "ACTIVE",
    "requiresAttributes": [
        {
            "name": "com.amazonaws.ecs.capability.logging-driver.awslogs"
        },
        {
            "name": "ecs.capability.execution-role-awslogs"
        },
        {
            "name": "com.amazonaws.ecs.capability.ecr-auth"
        },
        {
            "name": "com.amazonaws.ecs.capability.docker-remote-api.1.19"
        },
        {
            "name": "ecs.capability.execution-role-ecr-pull"
        },
        {
            "name": "com.amazonaws.ecs.capability.docker-remote-api.1.18"
        },
        {
            "name": "ecs.capability.task-eni"
        },
        {
            "name": "com.amazonaws.ecs.capability.docker-remote-api.1.29"
        }
    ],
    "placementConstraints": [],
    "compatibilities": [
        "EC2",
        "FARGATE"
    ],
    "requiresCompatibilities": [
        "EC2",
        "FARGATE"
    ],
    "cpu": "256",
    "memory": "1024",
    "runtimePlatform": {
        "cpuArchitecture": "X86_64",
        "operatingSystemFamily": "LINUX"
    },
    "registeredAt": "2023-06-02T04:22:33.585Z",
    "registeredBy": "arn:aws:iam::926780917917:user/RandallS",
    "tags": []
}
